illumio_mcp/__init__.py
illumio_mcp/server.py
mseep_illumio_mcp-0.1.3.dist-info/METADATA
mseep_illumio_mcp-0.1.3.dist-info/WHEEL
mseep_illumio_mcp-0.1.3.dist-info/entry_points.txt
mseep_illumio_mcp-0.1.3.dist-info/licenses/LICENSE
mseep_illumio_mcp-0.1.3.dist-info/RECORD
