Metadata-Version: 2.4
Name: mseep-illumio-mcp
Version: 0.1.3
Summary: A MCP server project
Author-email: mseep <support@skydeck.ai>
License-File: LICENSE
Requires-Python: >=3.12
Requires-Dist: illumio>=1.1.3
Requires-Dist: logging>=0.4.9.6
Requires-Dist: mcp>=1.2.0
Requires-Dist: pandas>=2.2.3
Requires-Dist: python-dotenv>=1.0.1
